[
  {
    "block": "00:00",
    "count": 18,
    "activity_level": "Low",
    "temperature": 12.8,
    "wind_speed_mps": 4.61,
    "humidity": 75,
    "environment_score": 1.3,
    "environment_label": "Poor"
  },
  {
    "block": "00:15",
    "count": 17,
    "activity_level": "Low",
    "temperature": 13.73,
    "wind_speed_mps": 6.69,
    "humidity": 77,
    "environment_score": 1.0,
    "environment_label": "Poor"
  },
  {
    "block": "00:30",
    "count": 48,
    "activity_level": "Low",
    "temperature": 13.73,
    "wind_speed_mps": 6.69,
    "humidity": 77,
    "environment_score": 1.0,
    "environment_label": "Poor"
  },
  {
    "block": "00:45",
    "count": 73,
    "activity_level": "Low",
    "temperature": 13.79,
    "wind_speed_mps": 6.69,
    "humidity": 77,
    "environment_score": 1.0,
    "environment_label": "Poor"
  },
  {
    "block": "01:00",
    "count": 66,
    "activity_level": "Low",
    "temperature": 12.8,
    "wind_speed_mps": 4.32,
    "humidity": 78,
    "environment_score": 1.3,
    "environment_label": "Poor"
  },
  {
    "block": "01:15",
    "count": 63,
    "activity_level": "Low",
    "temperature": 12.79,
    "wind_speed_mps": 3.09,
    "humidity": 82,
    "environment_score": 1.6,
    "environment_label": "Marginal"
  },
  {
    "block": "01:30",
    "count": 66,
    "activity_level": "Low",
    "temperature": 12.86,
    "wind_speed_mps": 3.09,
    "humidity": 82,
    "environment_score": 1.6,
    "environment_label": "Marginal"
  },
  {
    "block": "01:45",
    "count": 34,
    "activity_level": "Low",
    "temperature": 12.86,
    "wind_speed_mps": 3.09,
    "humidity": 82,
    "environment_score": 1.6,
    "environment_label": "Marginal"
  },
  {
    "block": "02:00",
    "count": 33,
    "activity_level": "Low",
    "temperature": 14.79,
    "wind_speed_mps": 4.63,
    "humidity": 77,
    "environment_score": 1.3,
    "environment_label": "Poor"
  },
  {
    "block": "02:15",
    "count": 25,
    "activity_level": "Low",
    "temperature": 15.79,
    "wind_speed_mps": 5.14,
    "humidity": 77,
    "environment_score": 2.3,
    "environment_label": "Marginal"
  },
  {
    "block": "02:30",
    "count": 30,
    "activity_level": "Low",
    "temperature": 15.66,
    "wind_speed_mps": 5.14,
    "humidity": 77,
    "environment_score": 2.3,
    "environment_label": "Marginal"
  },
  {
    "block": "02:45",
    "count": 50,
    "activity_level": "Low",
    "temperature": 15.66,
    "wind_speed_mps": 5.14,
    "humidity": 77,
    "environment_score": 2.3,
    "environment_label": "Marginal"
  },
  {
    "block": "03:00",
    "count": 86,
    "activity_level": "Low",
    "temperature": 13.8,
    "wind_speed_mps": 4.56,
    "humidity": 80,
    "environment_score": 1.3,
    "environment_label": "Poor"
  },
  {
    "block": "03:15",
    "count": 57,
    "activity_level": "Low",
    "temperature": 15.66,
    "wind_speed_mps": 4.12,
    "humidity": 77,
    "environment_score": 2.3,
    "environment_label": "Marginal"
  },
  {
    "block": "03:30",
    "count": 95,
    "activity_level": "Low",
    "temperature": 15.09,
    "wind_speed_mps": 4.12,
    "humidity": 75,
    "environment_score": 2.3,
    "environment_label": "Marginal"
  },
  {
    "block": "03:45",
    "count": 38,
    "activity_level": "Low",
    "temperature": 15.09,
    "wind_speed_mps": 4.12,
    "humidity": 76,
    "environment_score": 2.3,
    "environment_label": "Marginal"
  },
  {
    "block": "04:00",
    "count": 50,
    "activity_level": "Low",
    "temperature": 14.6,
    "wind_speed_mps": 4.63,
    "humidity": 76,
    "environment_score": 1.3,
    "environment_label": "Poor"
  },
  {
    "block": "04:15",
    "count": 6,
    "activity_level": "Low",
    "temperature": 13.95,
    "wind_speed_mps": 4.63,
    "humidity": 83,
    "environment_score": 1.3,
    "environment_label": "Poor"
  },
  {
    "block": "04:30",
    "count": 8,
    "activity_level": "Low",
    "temperature": 13.93,
    "wind_speed_mps": 4.63,
    "humidity": 84,
    "environment_score": 1.3,
    "environment_label": "Poor"
  },
  {
    "block": "04:45",
    "count": 21,
    "activity_level": "Low",
    "temperature": 13.93,
    "wind_speed_mps": 4.63,
    "humidity": 85,
    "environment_score": 1.3,
    "environment_label": "Poor"
  },
  {
    "block": "05:00",
    "count": 9,
    "activity_level": "Low",
    "temperature": 13.93,
    "wind_speed_mps": 4.12,
    "humidity": 88,
    "environment_score": 1.3,
    "environment_label": "Poor"
  },
  {
    "block": "05:15",
    "count": 89,
    "activity_level": "Low",
    "temperature": 14.17,
    "wind_speed_mps": 4.12,
    "humidity": 85,
    "environment_score": 1.3,
    "environment_label": "Poor"
  },
  {
    "block": "05:30",
    "count": 48,
    "activity_level": "Low",
    "temperature": 14.17,
    "wind_speed_mps": 4.63,
    "humidity": 85,
    "environment_score": 1.3,
    "environment_label": "Poor"
  },
  {
    "block": "05:45",
    "count": 37,
    "activity_level": "Low",
    "temperature": 14.17,
    "wind_speed_mps": 4.63,
    "humidity": 86,
    "environment_score": 1.3,
    "environment_label": "Poor"
  },
  {
    "block": "06:00",
    "count": 34,
    "activity_level": "Low",
    "temperature": 13.93,
    "wind_speed_mps": 4.12,
    "humidity": 88,
    "environment_score": 1.3,
    "environment_label": "Poor"
  },
  {
    "block": "06:15",
    "count": 44,
    "activity_level": "Low",
    "temperature": 14.34,
    "wind_speed_mps": 4.12,
    "humidity": 87,
    "environment_score": 1.3,
    "environment_label": "Poor"
  },
  {
    "block": "06:30",
    "count": 46,
    "activity_level": "Low",
    "temperature": 14.34,
    "wind_speed_mps": 4.12,
    "humidity": 86,
    "environment_score": 1.3,
    "environment_label": "Poor"
  },
  {
    "block": "06:45",
    "count": 65,
    "activity_level": "Low",
    "temperature": 14.59,
    "wind_speed_mps": 4.63,
    "humidity": 84,
    "environment_score": 1.3,
    "environment_label": "Poor"
  },
  {
    "block": "07:00",
    "count": 108,
    "activity_level": "Low",
    "temperature": 14.59,
    "wind_speed_mps": 5.66,
    "humidity": 84,
    "environment_score": 1.3,
    "environment_label": "Poor"
  },
  {
    "block": "07:15",
    "count": 99,
    "activity_level": "Low",
    "temperature": 15,
    "wind_speed_mps": 5.14,
    "humidity": 83,
    "environment_score": 2.3,
    "environment_label": "Marginal"
  },
  {
    "block": "07:30",
    "count": 150,
    "activity_level": "Low",
    "temperature": 15.02,
    "wind_speed_mps": 5.14,
    "humidity": 82,
    "environment_score": 2.3,
    "environment_label": "Marginal"
  },
  {
    "block": "07:45",
    "count": 182,
    "activity_level": "Low",
    "temperature": 15.42,
    "wind_speed_mps": 5.14,
    "humidity": 81,
    "environment_score": 2.3,
    "environment_label": "Marginal"
  },
  {
    "block": "08:00",
    "count": 180,
    "activity_level": "Low",
    "temperature": 15.67,
    "wind_speed_mps": 3.6,
    "humidity": 82,
    "environment_score": 2.3,
    "environment_label": "Marginal"
  },
  {
    "block": "08:15",
    "count": 225,
    "activity_level": "Low",
    "temperature": 14.79,
    "wind_speed_mps": 3.6,
    "humidity": 88,
    "environment_score": 1.3,
    "environment_label": "Poor"
  },
  {
    "block": "08:30",
    "count": 315,
    "activity_level": "Low",
    "temperature": 16.51,
    "wind_speed_mps": 3.6,
    "humidity": 80,
    "environment_score": 2.3,
    "environment_label": "Marginal"
  },
  {
    "block": "08:45",
    "count": 457,
    "activity_level": "Low",
    "temperature": 14.86,
    "wind_speed_mps": 3.6,
    "humidity": 88,
    "environment_score": 1.3,
    "environment_label": "Poor"
  },
  {
    "block": "09:00",
    "count": 655,
    "activity_level": "Medium",
    "temperature": 14.86,
    "wind_speed_mps": 6.17,
    "humidity": 88,
    "environment_score": 1.0,
    "environment_label": "Poor"
  },
  {
    "block": "09:15",
    "count": 746,
    "activity_level": "Medium",
    "temperature": 17.32,
    "wind_speed_mps": 6.17,
    "humidity": 78,
    "environment_score": 2.0,
    "environment_label": "Marginal"
  },
  {
    "block": "09:30",
    "count": 849,
    "activity_level": "Medium",
    "temperature": 18.17,
    "wind_speed_mps": 3.13,
    "humidity": 73,
    "environment_score": 2.5,
    "environment_label": "Favourable"
  },
  {
    "block": "09:45",
    "count": 879,
    "activity_level": "Medium",
    "temperature": 18.72,
    "wind_speed_mps": 2.68,
    "humidity": 71,
    "environment_score": 2.8,
    "environment_label": "Favourable"
  },
  {
    "block": "10:00",
    "count": 1097,
    "activity_level": "High",
    "temperature": 18,
    "wind_speed_mps": 8.75,
    "humidity": 78,
    "environment_score": 2.0,
    "environment_label": "Marginal"
  },
  {
    "block": "10:15",
    "count": 1214,
    "activity_level": "High",
    "temperature": 18,
    "wind_speed_mps": 8.75,
    "humidity": 77,
    "environment_score": 2.0,
    "environment_label": "Marginal"
  },
  {
    "block": "10:30",
    "count": 1149,
    "activity_level": "High",
    "temperature": 18.74,
    "wind_speed_mps": 3.13,
    "humidity": 69,
    "environment_score": 2.5,
    "environment_label": "Favourable"
  },
  {
    "block": "10:45",
    "count": 1195,
    "activity_level": "High",
    "temperature": 19.28,
    "wind_speed_mps": 3.58,
    "humidity": 70,
    "environment_score": 2.5,
    "environment_label": "Favourable"
  },
  {
    "block": "11:00",
    "count": 1047,
    "activity_level": "High",
    "temperature": 19.82,
    "wind_speed_mps": 3.13,
    "humidity": 69,
    "environment_score": 2.5,
    "environment_label": "Favourable"
  },
  {
    "block": "11:15",
    "count": 1199,
    "activity_level": "High",
    "temperature": 19.82,
    "wind_speed_mps": 3.13,
    "humidity": 70,
    "environment_score": 2.5,
    "environment_label": "Favourable"
  },
  {
    "block": "11:30",
    "count": 1267,
    "activity_level": "High",
    "temperature": 19.85,
    "wind_speed_mps": 3.58,
    "humidity": 71,
    "environment_score": 2.5,
    "environment_label": "Favourable"
  },
  {
    "block": "11:45",
    "count": 1252,
    "activity_level": "High",
    "temperature": 19.85,
    "wind_speed_mps": 3.13,
    "humidity": 67,
    "environment_score": 2.5,
    "environment_label": "Favourable"
  },
  {
    "block": "12:00",
    "count": 850,
    "activity_level": "Medium",
    "temperature": 21.66,
    "wind_speed_mps": 8.75,
    "humidity": 73,
    "environment_score": 2.2,
    "environment_label": "Marginal"
  },
  {
    "block": "12:15",
    "count": 594,
    "activity_level": "Medium",
    "temperature": 21.79,
    "wind_speed_mps": 8.75,
    "humidity": 73,
    "environment_score": 2.2,
    "environment_label": "Marginal"
  },
  {
    "block": "12:30",
    "count": 557,
    "activity_level": "Medium",
    "temperature": 21.79,
    "wind_speed_mps": 8.75,
    "humidity": 73,
    "environment_score": 2.2,
    "environment_label": "Marginal"
  },
  {
    "block": "12:45",
    "count": 482,
    "activity_level": "Low",
    "temperature": 21.79,
    "wind_speed_mps": 8.75,
    "humidity": 73,
    "environment_score": 2.2,
    "environment_label": "Marginal"
  },
  {
    "block": "13:00",
    "count": 328,
    "activity_level": "Low",
    "temperature": 20.92,
    "wind_speed_mps": 9.77,
    "humidity": 64,
    "environment_score": 1.9,
    "environment_label": "Marginal"
  }
]